myexceptions/__init__.py
myexceptions/exceptions.py
myexceptions-0.1.0.dist-info/METADATA
myexceptions-0.1.0.dist-info/WHEEL
myexceptions-0.1.0.dist-info/top_level.txt
myexceptions-0.1.0.dist-info/RECORD
