Metadata-Version: 2.4
Name: myexceptions
Version: 0.1.0
Summary: Add your description here
Home-page: 
Author: abrun
Requires-Python: >=3.10
Requires-Dist: setuptools>=80.9.0
Requires-Dist: wheel>=0.45.1
Dynamic: author
Dynamic: requires-python
